datastorm/__init__.py
datastorm/base.py
datastorm/datastorm.py
datastorm/entity.py
datastorm/exceptions/__init__.py
datastorm/exceptions/base.py
datastorm/exceptions/datastore.py
datastorm/fields.py
datastorm/filter.py
datastorm/limits/__init__.py
datastorm/limits/batching.py
datastorm/mapper.py
datastorm/query.py
datastorm/utils/__init__.py
datastorm/utils/batching.py
datastorm-0.0.0a8.dist-info/LICENSE
datastorm-0.0.0a8.dist-info/WHEEL
datastorm-0.0.0a8.dist-info/METADATA
datastorm-0.0.0a8.dist-info/RECORD
